custom_uuid/__init__.py
custom_uuid/main.py
custom_uuid/templates/__init__.py
custom_uuid/templates/main.py
custom_uuid-11.9.23.1.dist-info/LICENSE
custom_uuid-11.9.23.1.dist-info/METADATA
custom_uuid-11.9.23.1.dist-info/WHEEL
custom_uuid-11.9.23.1.dist-info/RECORD
