Metadata-Version: 2.1
Name: custom_uuid
Version: 11.9.23.1
Summary: Easily generate meaningful & consistent UUID's without the excessive boilerplate normally required.
License: MIT
Author: kdcokenny
Author-email: kenny@kdco.llc
Requires-Python: >=3.10
Classifier: License :: OSI Approved :: MIT License
Classifier: Programming Language :: Python :: 3
Classifier: Programming Language :: Python :: 3.10
Classifier: Programming Language :: Python :: 3.11
